pyBASS/BASS.py
pyBASS/__init__.py
pyBASS/sobol.py
pyBASS/sobol_mc.py
pyBASS/utils.py
pybass_emu-0.8.1.dist-info/licenses/LICENSE
pybass_emu-0.8.1.dist-info/METADATA
pybass_emu-0.8.1.dist-info/WHEEL
pybass_emu-0.8.1.dist-info/top_level.txt
pybass_emu-0.8.1.dist-info/RECORD
