Metadata-Version: 2.4
Name: pybass-emu
Version: 0.8.1
Summary: Bayesian Adaptive Spline Surfaces
Author-email: Devin Francom <dfrancom@lanl.gov>, Arthur Lui <luiarthur@gmail.com>, "J. Derek Tucker" <jdtuck@sandia.gov>
License-Expression: BSD-3-Clause
Project-URL: repository, http://www.github.com/lanl/pybass
Project-URL: Repository, https://github.com/lanl/pybass
Project-URL: Issues, https://github.com/lanl/pybass/issues
Keywords: emulator
Classifier: Operating System :: OS Independent
Classifier: Topic :: Scientific/Engineering
Classifier: Topic :: Scientific/Engineering :: Mathematics
Classifier: Programming Language :: Python :: 3.9
Classifier: Programming Language :: Python :: 3.10
Classifier: Programming Language :: Python :: 3.11
Classifier: Programming Language :: Python :: 3.12
Classifier: Programming Language :: Python :: 3.13
Classifier: Programming Language :: Python :: 3.14
Requires-Python: >=3.9
License-File: LICENSE
Requires-Dist: matplotlib>=3.7.3
Requires-Dist: numpy>=1.24.4
Requires-Dist: scipy>=1.10.1
Requires-Dist: pandas>=2.0.3
Dynamic: license-file
